MANIFEST.in
README.rst
requirements.txt
setup.py
gqUtil.egg-info/PKG-INFO
gqUtil.egg-info/SOURCES.txt
gqUtil.egg-info/dependency_links.txt
gqUtil.egg-info/requires.txt
gqUtil.egg-info/top_level.txt
myGq/__init__.py
myGq/findAllIndex.py